README.rst
picks
setup.py
picks.egg-info/PKG-INFO
picks.egg-info/SOURCES.txt
picks.egg-info/dependency_links.txt
picks.egg-info/requires.txt
picks.egg-info/top_level.txt
picks_core/__init__.py
picks_viewer/QTDark.stylesheet
picks_viewer/__init__.py
picks_viewer/picks.ui