Metadata-Version: 1.1
Name: picks
Version: 0.6.4
Summary: A picture viewer, tagger and picker
Home-page: https://github.com/frans-fuerst/picks
Author: Frans Fuerst
Author-email: frans.fuerst+github@gmail.com
License: MIT
Keywords: picks image picture viewer choose pick tagging slideshow gallery
Platform: UNKNOWN
Classifier: Development Status :: 3 - Alpha
Classifier: Programming Language :: Python :: 3
